ipa/__init__.py
ipa/common/__init__.py
ipa/common/eclipse_api.py
ipa/common/utils.py
ipa/dash/__init__.py
ipa/dash/report.py
ipa/dash/run.py
ipa/dash/assets/eclipse-dash.jar
ipa/generic/__init__.py
ipa/generic/local.py
ipa/generic/remote.py
ipa/ghub/__init__.py
ipa/ghub/remote.py
ipa/glab/__init__.py
ipa/glab/ci.py
ipa/glab/remote.py
ipa/templates/default_report.jinja
ipa/templates/default_report_dl.jinja
ipa/templates/review_report.jinja
ipa/templates/review_report_dl.jinja
eclipse_ipa-0.1.3.dist-info/METADATA
eclipse_ipa-0.1.3.dist-info/WHEEL
eclipse_ipa-0.1.3.dist-info/entry_points.txt
eclipse_ipa-0.1.3.dist-info/licenses/LICENSE
eclipse_ipa-0.1.3.dist-info/licenses/NOTICE.md
eclipse_ipa-0.1.3.dist-info/RECORD
