Metadata-Version: 2.4
Name: eclipse-ipa
Version: 0.1.3
Summary: Tool to perform IP Analysis for GitHub and GitLab repositories.
Project-URL: Homepage, https://projects.eclipse.org/projects/technology.dash
Project-URL: Source, https://gitlab.eclipse.org/eclipse/technology/dash/ip-analysis
Project-URL: Changelog, https://gitlab.eclipse.org/eclipse/technology/dash/ip-analysis/-/blob/main/CHANGELOG.md
Author-email: André Gomes <andre.gomes@eclipse-foundation.org>
License-File: LICENSE
License-File: NOTICE.md
Classifier: Development Status :: 5 - Production/Stable
Classifier: Environment :: Console
Classifier: Intended Audience :: Developers
Classifier: License :: OSI Approved :: Eclipse Public License 2.0 (EPL-2.0)
Classifier: Operating System :: OS Independent
Classifier: Programming Language :: Python :: 3.10
Classifier: Programming Language :: Python :: 3.11
Classifier: Programming Language :: Python :: 3.12
Classifier: Programming Language :: Python :: 3.13
Classifier: Programming Language :: Python :: 3.14
Requires-Python: >=3.10
Requires-Dist: chardet==5.2.0
Requires-Dist: colorama==0.4.6
Requires-Dist: jinja2==3.1.6
Requires-Dist: pygithub==2.8.1
Requires-Dist: python-gitlab==7.0.0
Requires-Dist: requests==2.32.5
